{"cards":[{"type":0,"content":"After blacking out during New Year's Eve, I was awoken by _."},{"type":0,"content":"This holiday season, Tim Allen must overcome his fear of _ to save Christmas."},{"type":0,"content":"Jesus is _."},{"type":0,"content":"Every Christmas, my uncle gets drunk and tells the story about _."},{"type":0,"content":"What keeps me warm during the cold, cold winter?"},{"type":0,"content":"On the third day of Christmas, my true love gave to me: three French hens, two turtle doves, and _."},{"type":0,"content":"Wake up, America. Christmas is under attack by secular liberals and their _."},{"t":1,"content":"Santa's heavy sack."},{"t":1,"content":"Clearing a bloody path through Walmart with a scimitar."},{"t":1,"content":"Another shitty year."},{"t":1,"content":"Whatever Kwanzaa is supposed to be about."},{"t":1,"content":"A Christmas stocking full of coleslaw."},{"t":1,"content":"Elf cum."},{"t":1,"content":"The tiny, calloused hands of the Chinese children that made this card."},{"t":1,"content":"Taking down Santa with a surface-to-air missle."},{"t":1,"content":"Several intertwining love stories featuring Hugh Grant."},{"t":1,"content":"Mall Santa."},{"t":1,"content":"My hot cousin."},{"t":1,"content":"The Star Wars Holiday Special."},{"t":1,"content":"Krampus, the Austrian Christmas monster."},{"t":1,"content":"Pretending to be happy."},{"t":1,"content":"Socks. "},{"t":1,"content":"Eating an entire snowman."},{"t":1,"content":"A toxic family environment."},{"t":1,"content":"A visually arresting turtleneck."},{"t":1,"content":"Fucking up \"Silent Night\" in front of 300 parents."},{"t":1,"content":"Immaculate conception."},{"t":1,"content":"Space Jam on VHS."},{"t":1,"content":"Gift-wrapping a live hamster."},{"t":1,"content":"A Hungry-Man&trade; Frozen Christmas Dinner for One."}],"name":"2012 Holiday Pack"}